[
    {
        "name": "n_estimators",
        "short_descr": "The number of trees in the forest.",
        "type": "int",
        "min_val": 1,
        "max_val": 500,
        "default_val": 100
    },
    {
        "name": "max_depth",
        "short_descr": "The maximum depth of the tree.",
        "type": "int",
        "min_val": 1,
        "max_val": 10,
        "default_val": 3
    },
    {
        "name": "min_samples_split",
        "short_descr": "The minimum number of samples required to split an internal node.",
        "type": "float",
        "min_val": 0,
        "max_val": 1,
        "default_val": 0.1
    },
    {
        "name": "min_weight_fraction_leaf",
        "short_descr": "The minimum weighted fraction of the sum total of weights (of all the input samples) required to be at a leaf node.",
        "type": "float",
        "min_val": 0,
        "max_val": 0.5,
        "default_val": 0
    }
]